qui/__init__.py
qui/constants.py
qui/exceptions.py
qui/j2template.py
qui/settings.py
qui/templates/manifest.json
qui/templates/qui.html
qui/templates/service-worker.js
qui/web/__init__.py
qui/web/tornado.py
qui_server-1.19.1.dist-info/licenses/LICENSE.txt
qui_server-1.19.1.dist-info/METADATA
qui_server-1.19.1.dist-info/WHEEL
qui_server-1.19.1.dist-info/top_level.txt
qui_server-1.19.1.dist-info/RECORD
