Metadata-Version: 2.4
Name: qui-server
Version: 1.19.1
Summary: A fully fledged qToggle implementation written in Python
Author-email: Calin Crisan <ccrisan@gmail.com>
License: Apache 2.0
Requires-Python: >=3.11
License-File: LICENSE.txt
Requires-Dist: jinja2
Requires-Dist: tornado
Dynamic: license-file
